[
    {
      "cooperativa": "Nord",
      "conta": 881722,
      "cliente": "Nichols Carpenter",
      "proposta": 998174685,
      "data": "30-11-2018"
    },
    {
      "cooperativa": "Moquino",
      "conta": 511022,
      "cliente": "Copeland Spears",
      "proposta": 645322732,
      "data": "30-11-2018"
    },
    {
      "cooperativa": "Enetai",
      "conta": 807355,
      "cliente": "Perry Mcintyre",
      "proposta": 171316782,
      "data": "30-11-2018"
    },
    {
      "cooperativa": "Trexlertown",
      "conta": 728018,
      "cliente": "Mccarthy Valencia",
      "proposta": 434702741,
      "data": "30-11-2018"
    },
    {
      "cooperativa": "Succasunna",
      "conta": 657743,
      "cliente": "Fischer Larsen",
      "proposta": 111419199,
      "data": "30-11-2018"
    },
    {
      "cooperativa": "Cartwright",
      "conta": 972729,
      "cliente": "Watson Olsen",
      "proposta": 553608818,
      "data": "30-11-2018"
    },
    {
      "cooperativa": "Franklin",
      "conta": 373318,
      "cliente": "Curtis Perez",
      "proposta": 708752239,
      "data": "30-11-2018"
    },
    {
      "cooperativa": "Canterwood",
      "conta": 341057,
      "cliente": "Atkinson Heath",
      "proposta": 178294887,
      "data": "30-11-2018"
    },
    {
      "cooperativa": "Winesburg",
      "conta": 507138,
      "cliente": "Sears Rios",
      "proposta": 150882833,
      "data": "30-11-2018"
    },
    {
      "cooperativa": "Kieler",
      "conta": 154856,
      "cliente": "Larsen Atkins",
      "proposta": 461063076,
      "data": "30-11-2018"
    },
    {
      "cooperativa": "Marienthal",
      "conta": 871167,
      "cliente": "Melton Hines",
      "proposta": 800217666,
      "data": "30-11-2018"
    },
    {
      "cooperativa": "Lutsen",
      "conta": 679990,
      "cliente": "Wagner Callahan",
      "proposta": 300808045,
      "data": "30-11-2018"
    },
    {
      "cooperativa": "Darrtown",
      "conta": 149302,
      "cliente": "Wilkerson Pierce",
      "proposta": 116025475,
      "data": "30-11-2018"
    },
    {
      "cooperativa": "Ticonderoga",
      "conta": 451981,
      "cliente": "Harvey Sexton",
      "proposta": 683270196,
      "data": "30-11-2018"
    },
    {
      "cooperativa": "Hackneyville",
      "conta": 608528,
      "cliente": "Graves Walter",
      "proposta": 768440455,
      "data": "30-11-2018"
    },
    {
      "cooperativa": "Mayfair",
      "conta": 249209,
      "cliente": "Chavez Obrien",
      "proposta": 803016599,
      "data": "30-11-2018"
    },
    {
      "cooperativa": "Libertytown",
      "conta": 225021,
      "cliente": "Sanford Ochoa",
      "proposta": 528033248,
      "data": "30-11-2018"
    },
    {
      "cooperativa": "Edneyville",
      "conta": 556164,
      "cliente": "Rocha Sargent",
      "proposta": 776449085,
      "data": "30-11-2018"
    },
    {
      "cooperativa": "Springhill",
      "conta": 941807,
      "cliente": "Wilson Hayden",
      "proposta": 144083504,
      "data": "30-11-2018"
    },
    {
      "cooperativa": "Brooktrails",
      "conta": 770564,
      "cliente": "Summers Conner",
      "proposta": 343993016,
      "data": "30-11-2018"
    },
    {
      "cooperativa": "Conestoga",
      "conta": 647114,
      "cliente": "Maynard Dudley",
      "proposta": 393999576,
      "data": "30-11-2018"
    },
    {
      "cooperativa": "Utting",
      "conta": 793885,
      "cliente": "Potts Davis",
      "proposta": 405776480,
      "data": "30-11-2018"
    },
    {
      "cooperativa": "Geyserville",
      "conta": 249395,
      "cliente": "Huff Houston",
      "proposta": 454313861,
      "data": "30-11-2018"
    },
    {
      "cooperativa": "Wollochet",
      "conta": 749466,
      "cliente": "Tanner Riley",
      "proposta": 806782585,
      "data": "30-11-2018"
    },
    {
      "cooperativa": "Marenisco",
      "conta": 514428,
      "cliente": "Green Morrison",
      "proposta": 861774304,
      "data": "30-11-2018"
    },
    {
      "cooperativa": "Shawmut",
      "conta": 485225,
      "cliente": "Suarez Martin",
      "proposta": 883910374,
      "data": "30-11-2018"
    },
    {
      "cooperativa": "Dawn",
      "conta": 829014,
      "cliente": "Garner Ayala",
      "proposta": 122338880,
      "data": "30-11-2018"
    },
    {
      "cooperativa": "Remington",
      "conta": 574028,
      "cliente": "Acosta Mayer",
      "proposta": 492803848,
      "data": "30-11-2018"
    },
    {
      "cooperativa": "Oley",
      "conta": 646547,
      "cliente": "Cross Park",
      "proposta": 963176841,
      "data": "30-11-2018"
    },
    {
      "cooperativa": "Welda",
      "conta": 806128,
      "cliente": "Rojas Walsh",
      "proposta": 698560419,
      "data": "30-11-2018"
    },
    {
      "cooperativa": "Tonopah",
      "conta": 892210,
      "cliente": "Melendez Blair",
      "proposta": 498722613,
      "data": "30-11-2018"
    },
    {
      "cooperativa": "Nanafalia",
      "conta": 728899,
      "cliente": "Knox Snider",
      "proposta": 621994522,
      "data": "30-11-2018"
    },
    {
      "cooperativa": "Dragoon",
      "conta": 506651,
      "cliente": "Lopez Allen",
      "proposta": 285310953,
      "data": "30-11-2018"
    },
    {
      "cooperativa": "Romeville",
      "conta": 118984,
      "cliente": "Hopkins Glenn",
      "proposta": 922904258,
      "data": "30-11-2018"
    },
    {
      "cooperativa": "Joppa",
      "conta": 380582,
      "cliente": "Ayala Lee",
      "proposta": 526160382,
      "data": "30-11-2018"
    },
    {
      "cooperativa": "Chestnut",
      "conta": 253934,
      "cliente": "Meyer Golden",
      "proposta": 657876386,
      "data": "30-11-2018"
    },
    {
      "cooperativa": "Kraemer",
      "conta": 504729,
      "cliente": "Todd Bell",
      "proposta": 318468926,
      "data": "30-11-2018"
    },
    {
      "cooperativa": "Grantville",
      "conta": 705941,
      "cliente": "Ingram Dillard",
      "proposta": 378017355,
      "data": "30-11-2018"
    },
    {
      "cooperativa": "Malo",
      "conta": 295749,
      "cliente": "Leonard Mcintosh",
      "proposta": 768511305,
      "data": "30-11-2018"
    },
    {
      "cooperativa": "Itmann",
      "conta": 217258,
      "cliente": "Pope Simmons",
      "proposta": 810301335,
      "data": "30-11-2018"
    },
    {
      "cooperativa": "Harleigh",
      "conta": 716176,
      "cliente": "Schneider Ingram",
      "proposta": 800191748,
      "data": "30-11-2018"
    },
    {
      "cooperativa": "Staples",
      "conta": 495290,
      "cliente": "England Orr",
      "proposta": 852430757,
      "data": "30-11-2018"
    },
    {
      "cooperativa": "Berlin",
      "conta": 914474,
      "cliente": "Frye Sanders",
      "proposta": 373739682,
      "data": "30-11-2018"
    },
    {
      "cooperativa": "Morningside",
      "conta": 446622,
      "cliente": "Rice Patton",
      "proposta": 467045026,
      "data": "30-11-2018"
    },
    {
      "cooperativa": "Summerset",
      "conta": 656364,
      "cliente": "Ashley Brady",
      "proposta": 938384175,
      "data": "30-11-2018"
    },
    {
      "cooperativa": "Collins",
      "conta": 965681,
      "cliente": "Cruz Strong",
      "proposta": 680234385,
      "data": "30-11-2018"
    },
    {
      "cooperativa": "Aguila",
      "conta": 274150,
      "cliente": "Johnson Weeks",
      "proposta": 774326072,
      "data": "30-11-2018"
    },
    {
      "cooperativa": "Washington",
      "conta": 335013,
      "cliente": "Guy Odonnell",
      "proposta": 761022615,
      "data": "30-11-2018"
    },
    {
      "cooperativa": "Hailesboro",
      "conta": 651479,
      "cliente": "Charles Henderson",
      "proposta": 543472007,
      "data": "30-11-2018"
    },
    {
      "cooperativa": "Bluffview",
      "conta": 832008,
      "cliente": "Abbott Ortiz",
      "proposta": 960380510,
      "data": "30-11-2018"
    },
    {
      "cooperativa": "Gulf",
      "conta": 567825,
      "cliente": "Daniels Tate",
      "proposta": 383035776,
      "data": "30-11-2018"
    },
    {
      "cooperativa": "Grenelefe",
      "conta": 489564,
      "cliente": "Ortiz Cole",
      "proposta": 485924443,
      "data": "30-11-2018"
    },
    {
      "cooperativa": "Oretta",
      "conta": 332992,
      "cliente": "Aguirre Wolf",
      "proposta": 402036090,
      "data": "30-11-2018"
    },
    {
      "cooperativa": "Southmont",
      "conta": 861599,
      "cliente": "Phelps Howe",
      "proposta": 807004788,
      "data": "30-11-2018"
    },
    {
      "cooperativa": "Veyo",
      "conta": 198308,
      "cliente": "Finley Sharp",
      "proposta": 834884414,
      "data": "30-11-2018"
    },
    {
      "cooperativa": "Bentley",
      "conta": 921107,
      "cliente": "Howell Frank",
      "proposta": 532544650,
      "data": "30-11-2018"
    },
    {
      "cooperativa": "Boomer",
      "conta": 709527,
      "cliente": "Watkins Carlson",
      "proposta": 862580090,
      "data": "30-11-2018"
    },
    {
      "cooperativa": "Day",
      "conta": 310265,
      "cliente": "Romero Contreras",
      "proposta": 349908738,
      "data": "30-11-2018"
    },
    {
      "cooperativa": "Clarksburg",
      "conta": 647919,
      "cliente": "Singleton Allison",
      "proposta": 908772235,
      "data": "30-11-2018"
    },
    {
      "cooperativa": "Trucksville",
      "conta": 424857,
      "cliente": "Bowen Daniels",
      "proposta": 488289033,
      "data": "30-11-2018"
    },
    {
      "cooperativa": "Harviell",
      "conta": 580106,
      "cliente": "Moreno Mays",
      "proposta": 156282576,
      "data": "30-11-2018"
    },
    {
      "cooperativa": "Emory",
      "conta": 510629,
      "cliente": "Carey Ross",
      "proposta": 931770052,
      "data": "30-11-2018"
    },
    {
      "cooperativa": "Tryon",
      "conta": 360326,
      "cliente": "Buckner Taylor",
      "proposta": 554589632,
      "data": "30-11-2018"
    },
    {
      "cooperativa": "Yorklyn",
      "conta": 244213,
      "cliente": "Strong Beasley",
      "proposta": 150351629,
      "data": "30-11-2018"
    },
    {
      "cooperativa": "Lowgap",
      "conta": 124063,
      "cliente": "Britt Robinson",
      "proposta": 826970545,
      "data": "30-11-2018"
    },
    {
      "cooperativa": "Hartsville/Hartley",
      "conta": 290152,
      "cliente": "Dennis Mccarty",
      "proposta": 877333842,
      "data": "30-11-2018"
    },
    {
      "cooperativa": "Retsof",
      "conta": 257534,
      "cliente": "Acevedo Nixon",
      "proposta": 159553019,
      "data": "30-11-2018"
    },
    {
      "cooperativa": "Austinburg",
      "conta": 567758,
      "cliente": "Meyers Figueroa",
      "proposta": 190167709,
      "data": "30-11-2018"
    },
    {
      "cooperativa": "Caspar",
      "conta": 279351,
      "cliente": "Guzman Key",
      "proposta": 527937303,
      "data": "30-11-2018"
    },
    {
      "cooperativa": "Montura",
      "conta": 274228,
      "cliente": "Hays Williams",
      "proposta": 158676990,
      "data": "30-11-2018"
    },
    {
      "cooperativa": "Fivepointville",
      "conta": 713446,
      "cliente": "Mason Hurley",
      "proposta": 243414589,
      "data": "30-11-2018"
    },
    {
      "cooperativa": "Rosine",
      "conta": 636816,
      "cliente": "Cortez Matthews",
      "proposta": 861944174,
      "data": "30-11-2018"
    },
    {
      "cooperativa": "Enoree",
      "conta": 297034,
      "cliente": "Robles Fox",
      "proposta": 715117613,
      "data": "30-11-2018"
    },
    {
      "cooperativa": "Haring",
      "conta": 430569,
      "cliente": "Solomon Mcknight",
      "proposta": 377613778,
      "data": "30-11-2018"
    },
    {
      "cooperativa": "Kimmell",
      "conta": 448018,
      "cliente": "Cleveland Clay",
      "proposta": 610809040,
      "data": "30-11-2018"
    },
    {
      "cooperativa": "Gilmore",
      "conta": 581737,
      "cliente": "Flynn Tyson",
      "proposta": 847178605,
      "data": "30-11-2018"
    },
    {
      "cooperativa": "Condon",
      "conta": 613444,
      "cliente": "Frost Levine",
      "proposta": 715744282,
      "data": "30-11-2018"
    },
    {
      "cooperativa": "Leroy",
      "conta": 972725,
      "cliente": "Mcfadden Knight",
      "proposta": 171496632,
      "data": "30-11-2018"
    },
    {
      "cooperativa": "Chalfant",
      "conta": 740694,
      "cliente": "Hebert Gonzalez",
      "proposta": 269472026,
      "data": "30-11-2018"
    },
    {
      "cooperativa": "Templeton",
      "conta": 491342,
      "cliente": "Adams Reynolds",
      "proposta": 431634406,
      "data": "30-11-2018"
    },
    {
      "cooperativa": "Camino",
      "conta": 453009,
      "cliente": "Gomez Oconnor",
      "proposta": 614642539,
      "data": "30-11-2018"
    },
    {
      "cooperativa": "Saticoy",
      "conta": 209239,
      "cliente": "Frederick Johnson",
      "proposta": 614303805,
      "data": "30-11-2018"
    },
    {
      "cooperativa": "Callaghan",
      "conta": 115627,
      "cliente": "Bush Donaldson",
      "proposta": 501513982,
      "data": "30-11-2018"
    },
    {
      "cooperativa": "Ellerslie",
      "conta": 511811,
      "cliente": "Price Carroll",
      "proposta": 592120180,
      "data": "30-11-2018"
    },
    {
      "cooperativa": "Caln",
      "conta": 880119,
      "cliente": "Horne Gentry",
      "proposta": 720322502,
      "data": "30-11-2018"
    },
    {
      "cooperativa": "Grapeview",
      "conta": 581147,
      "cliente": "Daugherty Cruz",
      "proposta": 532541393,
      "data": "30-11-2018"
    },
    {
      "cooperativa": "Townsend",
      "conta": 224973,
      "cliente": "Weber Bartlett",
      "proposta": 556230454,
      "data": "30-11-2018"
    },
    {
      "cooperativa": "Carlos",
      "conta": 122207,
      "cliente": "Fernandez Lara",
      "proposta": 179962843,
      "data": "30-11-2018"
    },
    {
      "cooperativa": "Rushford",
      "conta": 959801,
      "cliente": "Deleon Smith",
      "proposta": 278070101,
      "data": "30-11-2018"
    },
    {
      "cooperativa": "Como",
      "conta": 908098,
      "cliente": "Stevenson Stevenson",
      "proposta": 621342357,
      "data": "30-11-2018"
    },
    {
      "cooperativa": "Ona",
      "conta": 114519,
      "cliente": "Bishop Hewitt",
      "proposta": 774213705,
      "data": "30-11-2018"
    },
    {
      "cooperativa": "Cliff",
      "conta": 657487,
      "cliente": "Randall Acevedo",
      "proposta": 412511409,
      "data": "30-11-2018"
    },
    {
      "cooperativa": "Stewart",
      "conta": 548841,
      "cliente": "Simmons Diaz",
      "proposta": 444053300,
      "data": "30-11-2018"
    },
    {
      "cooperativa": "Outlook",
      "conta": 356260,
      "cliente": "Harmon Mccray",
      "proposta": 899922322,
      "data": "30-11-2018"
    },
    {
      "cooperativa": "Bloomington",
      "conta": 132377,
      "cliente": "Mosley Walters",
      "proposta": 985980220,
      "data": "30-11-2018"
    },
    {
      "cooperativa": "Diaperville",
      "conta": 845986,
      "cliente": "Armstrong Garcia",
      "proposta": 492508857,
      "data": "30-11-2018"
    },
    {
      "cooperativa": "Frizzleburg",
      "conta": 229430,
      "cliente": "Clark Huff",
      "proposta": 445465524,
      "data": "30-11-2018"
    },
    {
      "cooperativa": "Roulette",
      "conta": 607957,
      "cliente": "Hutchinson Cunningham",
      "proposta": 704147953,
      "data": "30-11-2018"
    },
    {
      "cooperativa": "Masthope",
      "conta": 529054,
      "cliente": "Adkins Puckett",
      "proposta": 737163339,
      "data": "30-11-2018"
    },
    {
      "cooperativa": "Clarktown",
      "conta": 754079,
      "cliente": "Marshall Cantrell",
      "proposta": 498185798,
      "data": "30-11-2018"
    },
    {
      "cooperativa": "Forbestown",
      "conta": 888371,
      "cliente": "Dean Burke",
      "proposta": 528300496,
      "data": "30-11-2018"
    },
    {
      "cooperativa": "Weeksville",
      "conta": 465759,
      "cliente": "Richard Jennings",
      "proposta": 732095039,
      "data": "30-11-2018"
    },
    {
      "cooperativa": "Fidelis",
      "conta": 955480,
      "cliente": "Mcguire Sharpe",
      "proposta": 673791442,
      "data": "30-11-2018"
    },
    {
      "cooperativa": "Harrison",
      "conta": 380793,
      "cliente": "Santos Estes",
      "proposta": 411250185,
      "data": "30-11-2018"
    },
    {
      "cooperativa": "Shaft",
      "conta": 151443,
      "cliente": "Powell Brock",
      "proposta": 443401508,
      "data": "30-11-2018"
    },
    {
      "cooperativa": "Brule",
      "conta": 610832,
      "cliente": "Tillman Durham",
      "proposta": 624266647,
      "data": "30-11-2018"
    },
    {
      "cooperativa": "Sidman",
      "conta": 567875,
      "cliente": "Herrera Dunn",
      "proposta": 299428217,
      "data": "30-11-2018"
    },
    {
      "cooperativa": "Wiscon",
      "conta": 724684,
      "cliente": "Mejia Burns",
      "proposta": 405071325,
      "data": "30-11-2018"
    },
    {
      "cooperativa": "Clara",
      "conta": 357745,
      "cliente": "Cervantes Church",
      "proposta": 298161744,
      "data": "30-11-2018"
    },
    {
      "cooperativa": "Dana",
      "conta": 206568,
      "cliente": "Conway Ferguson",
      "proposta": 736860659,
      "data": "30-11-2018"
    },
    {
      "cooperativa": "Richford",
      "conta": 247143,
      "cliente": "Warner Hamilton",
      "proposta": 458732082,
      "data": "30-11-2018"
    },
    {
      "cooperativa": "Onton",
      "conta": 810149,
      "cliente": "Golden Gilbert",
      "proposta": 201950527,
      "data": "30-11-2018"
    },
    {
      "cooperativa": "Starks",
      "conta": 775893,
      "cliente": "Bright Mcfadden",
      "proposta": 994005472,
      "data": "30-11-2018"
    },
    {
      "cooperativa": "Shepardsville",
      "conta": 215836,
      "cliente": "Walter Delacruz",
      "proposta": 194521573,
      "data": "30-11-2018"
    },
    {
      "cooperativa": "Woodlake",
      "conta": 727676,
      "cliente": "Hodge Campbell",
      "proposta": 421631145,
      "data": "30-11-2018"
    },
    {
      "cooperativa": "Advance",
      "conta": 843817,
      "cliente": "Norton Sloan",
      "proposta": 787036406,
      "data": "30-11-2018"
    },
    {
      "cooperativa": "Kapowsin",
      "conta": 908167,
      "cliente": "Schroeder Mercer",
      "proposta": 295154972,
      "data": "30-11-2018"
    },
    {
      "cooperativa": "Ronco",
      "conta": 150392,
      "cliente": "Blevins Weber",
      "proposta": 620991705,
      "data": "30-11-2018"
    },
    {
      "cooperativa": "Avalon",
      "conta": 531858,
      "cliente": "Mcdonald Thornton",
      "proposta": 823872273,
      "data": "30-11-2018"
    },
    {
      "cooperativa": "Glasgow",
      "conta": 833567,
      "cliente": "Browning Mcmahon",
      "proposta": 672764233,
      "data": "30-11-2018"
    },
    {
      "cooperativa": "Coloma",
      "conta": 229522,
      "cliente": "Crane Mack",
      "proposta": 139668750,
      "data": "30-11-2018"
    },
    {
      "cooperativa": "Dale",
      "conta": 210600,
      "cliente": "Malone Petersen",
      "proposta": 132031650,
      "data": "30-11-2018"
    },
    {
      "cooperativa": "Camptown",
      "conta": 802911,
      "cliente": "Foley Tran",
      "proposta": 134387259,
      "data": "30-11-2018"
    },
    {
      "cooperativa": "Monument",
      "conta": 746008,
      "cliente": "Greene Nieves",
      "proposta": 862129219,
      "data": "30-11-2018"
    },
    {
      "cooperativa": "Carlton",
      "conta": 766758,
      "cliente": "Greer Leonard",
      "proposta": 586013742,
      "data": "30-11-2018"
    },
    {
      "cooperativa": "Kansas",
      "conta": 948606,
      "cliente": "Garrison Cortez",
      "proposta": 717381672,
      "data": "30-11-2018"
    },
    {
      "cooperativa": "Nipinnawasee",
      "conta": 550070,
      "cliente": "Cantrell Coleman",
      "proposta": 328680971,
      "data": "30-11-2018"
    },
    {
      "cooperativa": "Datil",
      "conta": 112907,
      "cliente": "Salas Mccall",
      "proposta": 530003618,
      "data": "30-11-2018"
    },
    {
      "cooperativa": "Sperryville",
      "conta": 124988,
      "cliente": "Pacheco Manning",
      "proposta": 900852907,
      "data": "30-11-2018"
    },
    {
      "cooperativa": "Layhill",
      "conta": 366392,
      "cliente": "Heath Vega",
      "proposta": 742347194,
      "data": "30-11-2018"
    },
    {
      "cooperativa": "Summertown",
      "conta": 391803,
      "cliente": "Avila Cabrera",
      "proposta": 690530223,
      "data": "30-11-2018"
    },
    {
      "cooperativa": "Glidden",
      "conta": 569510,
      "cliente": "Macias Quinn",
      "proposta": 853656367,
      "data": "30-11-2018"
    },
    {
      "cooperativa": "Falconaire",
      "conta": 433150,
      "cliente": "Keller Juarez",
      "proposta": 915138800,
      "data": "30-11-2018"
    },
    {
      "cooperativa": "Ahwahnee",
      "conta": 535000,
      "cliente": "Lyons Gill",
      "proposta": 385077172,
      "data": "30-11-2018"
    },
    {
      "cooperativa": "Gerton",
      "conta": 532697,
      "cliente": "Miranda Joyce",
      "proposta": 317555820,
      "data": "30-11-2018"
    },
    {
      "cooperativa": "Magnolia",
      "conta": 308549,
      "cliente": "Owens Britt",
      "proposta": 410521095,
      "data": "30-11-2018"
    },
    {
      "cooperativa": "Golconda",
      "conta": 694586,
      "cliente": "Hicks Clarke",
      "proposta": 977925834,
      "data": "30-11-2018"
    },
    {
      "cooperativa": "Zortman",
      "conta": 221487,
      "cliente": "Pena Brooks",
      "proposta": 124432532,
      "data": "30-11-2018"
    },
    {
      "cooperativa": "Westboro",
      "conta": 460150,
      "cliente": "Ware Scott",
      "proposta": 530892294,
      "data": "30-11-2018"
    },
    {
      "cooperativa": "Brambleton",
      "conta": 707917,
      "cliente": "Wooten Baird",
      "proposta": 976066423,
      "data": "30-11-2018"
    },
    {
      "cooperativa": "Orovada",
      "conta": 555896,
      "cliente": "Hunter Trevino",
      "proposta": 236121367,
      "data": "30-11-2018"
    },
    {
      "cooperativa": "Chamberino",
      "conta": 211121,
      "cliente": "Puckett Andrews",
      "proposta": 539649007,
      "data": "30-11-2018"
    },
    {
      "cooperativa": "Katonah",
      "conta": 885611,
      "cliente": "Oneill Pennington",
      "proposta": 251186960,
      "data": "30-11-2018"
    },
    {
      "cooperativa": "Robinson",
      "conta": 123926,
      "cliente": "Noel Carr",
      "proposta": 681062566,
      "data": "30-11-2018"
    },
    {
      "cooperativa": "Alamo",
      "conta": 314271,
      "cliente": "Valenzuela Hardin",
      "proposta": 609870116,
      "data": "30-11-2018"
    },
    {
      "cooperativa": "Eden",
      "conta": 158151,
      "cliente": "Barker Anthony",
      "proposta": 790781619,
      "data": "30-11-2018"
    },
    {
      "cooperativa": "Bodega",
      "conta": 660484,
      "cliente": "Orr Dale",
      "proposta": 922707803,
      "data": "30-11-2018"
    },
    {
      "cooperativa": "Chicopee",
      "conta": 938870,
      "cliente": "Frazier Vincent",
      "proposta": 895526450,
      "data": "30-11-2018"
    },
    {
      "cooperativa": "Albany",
      "conta": 228495,
      "cliente": "Sanders Valentine",
      "proposta": 395298371,
      "data": "30-11-2018"
    },
    {
      "cooperativa": "Odessa",
      "conta": 680328,
      "cliente": "Guthrie Ramirez",
      "proposta": 506434276,
      "data": "30-11-2018"
    },
    {
      "cooperativa": "Dante",
      "conta": 664207,
      "cliente": "Dickerson Thompson",
      "proposta": 838429559,
      "data": "30-11-2018"
    },
    {
      "cooperativa": "Riceville",
      "conta": 709513,
      "cliente": "Kline Leblanc",
      "proposta": 854891320,
      "data": "30-11-2018"
    },
    {
      "cooperativa": "Waumandee",
      "conta": 213780,
      "cliente": "Love Campos",
      "proposta": 259283694,
      "data": "30-11-2018"
    },
    {
      "cooperativa": "Saranap",
      "conta": 670711,
      "cliente": "Carr Cline",
      "proposta": 704957371,
      "data": "30-11-2018"
    },
    {
      "cooperativa": "Roberts",
      "conta": 211647,
      "cliente": "Reilly Hawkins",
      "proposta": 142490339,
      "data": "30-11-2018"
    },
    {
      "cooperativa": "Croom",
      "conta": 527309,
      "cliente": "West Chavez",
      "proposta": 809087569,
      "data": "30-11-2018"
    },
    {
      "cooperativa": "Strykersville",
      "conta": 994159,
      "cliente": "Short Bennett",
      "proposta": 182493715,
      "data": "30-11-2018"
    },
    {
      "cooperativa": "Rosburg",
      "conta": 691719,
      "cliente": "Pickett Lucas",
      "proposta": 629426433,
      "data": "30-11-2018"
    },
    {
      "cooperativa": "Cedarville",
      "conta": 264397,
      "cliente": "Dixon Bush",
      "proposta": 374638774,
      "data": "30-11-2018"
    },
    {
      "cooperativa": "Spokane",
      "conta": 142053,
      "cliente": "Floyd Edwards",
      "proposta": 536498182,
      "data": "30-11-2018"
    },
    {
      "cooperativa": "Castleton",
      "conta": 993666,
      "cliente": "Chapman Merritt",
      "proposta": 733448148,
      "data": "30-11-2018"
    },
    {
      "cooperativa": "Winston",
      "conta": 584767,
      "cliente": "Jennings Rollins",
      "proposta": 913172176,
      "data": "30-11-2018"
    },
    {
      "cooperativa": "Grill",
      "conta": 525102,
      "cliente": "Baldwin Oneil",
      "proposta": 553108587,
      "data": "30-11-2018"
    },
    {
      "cooperativa": "Vaughn",
      "conta": 496598,
      "cliente": "Griffith Lambert",
      "proposta": 582621846,
      "data": "30-11-2018"
    },
    {
      "cooperativa": "Caledonia",
      "conta": 177480,
      "cliente": "Ward Norman",
      "proposta": 137518743,
      "data": "30-11-2018"
    },
    {
      "cooperativa": "Rivers",
      "conta": 296819,
      "cliente": "Alvarez Swanson",
      "proposta": 695048153,
      "data": "30-11-2018"
    },
    {
      "cooperativa": "Rodanthe",
      "conta": 835078,
      "cliente": "Jenkins Romero",
      "proposta": 920928056,
      "data": "30-11-2018"
    },
    {
      "cooperativa": "Alden",
      "conta": 460917,
      "cliente": "Christensen Barnes",
      "proposta": 636034569,
      "data": "30-11-2018"
    },
    {
      "cooperativa": "Shasta",
      "conta": 407600,
      "cliente": "Rivera Lindsay",
      "proposta": 293739897,
      "data": "30-11-2018"
    },
    {
      "cooperativa": "Summerfield",
      "conta": 385944,
      "cliente": "Montoya Guerra",
      "proposta": 380105522,
      "data": "30-11-2018"
    },
    {
      "cooperativa": "Abiquiu",
      "conta": 983767,
      "cliente": "Phillips George",
      "proposta": 737327213,
      "data": "30-11-2018"
    },
    {
      "cooperativa": "Cotopaxi",
      "conta": 599765,
      "cliente": "Baker Sears",
      "proposta": 528449372,
      "data": "30-11-2018"
    },
    {
      "cooperativa": "Brewster",
      "conta": 448045,
      "cliente": "Mack Price",
      "proposta": 759473967,
      "data": "30-11-2018"
    },
    {
      "cooperativa": "Goochland",
      "conta": 837814,
      "cliente": "Carlson Morris",
      "proposta": 634419841,
      "data": "30-11-2018"
    }
  ]